batch_processor/__init__.py
batch_processor/batch_processor.py
batch_processor-0.0.3.dist-info/LICENSE
batch_processor-0.0.3.dist-info/METADATA
batch_processor-0.0.3.dist-info/WHEEL
batch_processor-0.0.3.dist-info/top_level.txt
batch_processor-0.0.3.dist-info/RECORD
