Metadata-Version: 2.1
Name: batch-processor
Version: 0.0.3
Summary: This library is used to enable batch processing by implementing python multiprocessing
Home-page: https://github.com/leon0707/batch_processor
License: UNKNOWN
Keywords: batch,multiprocessing,performance
Platform: UNKNOWN
Classifier: Development Status :: 3 - Alpha
Classifier: Programming Language :: Python :: 3.5
Classifier: Programming Language :: Python :: 3.6
Classifier: Programming Language :: Python :: 3.7
Classifier: Programming Language :: Python :: Implementation :: CPython
Classifier: Operating System :: OS Independent
Requires-Python: >=3.5
